MRFHelper/BuildingGeometry.py
MRFHelper/ConnectionAndBoundary.py
MRFHelper/LoadAndMaterial.py
MRFHelper/MRFhelper.py
MRFHelper/StructuralComponents.py
MRFHelper/UserCommand.py
MRFHelper/WriteInfo.py
MRFHelper/WriteScript.py
MRFHelper/__init__.py
MRFHelper/func.py
subroutines/BeamHinge.py
subroutines/ColumnHinge.py
subroutines/CyclicPushover.py
subroutines/DisplayModel2D.py
subroutines/PanelZone.py
subroutines/PushoverAnalysis.py
subroutines/Spring_Rigid.py
subroutines/Spring_Zero.py
subroutines/TimeHistorySolver.py
subroutines/__init__.py
mrfhelper-2.5.dist-info/LICENSE
mrfhelper-2.5.dist-info/METADATA
mrfhelper-2.5.dist-info/WHEEL
mrfhelper-2.5.dist-info/top_level.txt
mrfhelper-2.5.dist-info/RECORD
