Metadata-Version: 2.2
Name: mrfhelper
Version: 2.5
Summary: Generate tcl scripts of moment resisting frame for analysis using OpenSees
Author: Wenchen Lie
Author-email: 438171766@qq.com
Requires: matplotlib
Requires: wsection
License-File: LICENSE
Dynamic: author
Dynamic: author-email
Dynamic: requires
Dynamic: summary
